ms_python_client/__init__.py
ms_python_client/api_client.py
ms_python_client/cern_ms_api_client.py
ms_python_client/components/__init__.py
ms_python_client/components/events/__init__.py
ms_python_client/components/events/cern_events_component.py
ms_python_client/components/events/events_component.py
ms_python_client/components/users/__init__.py
ms_python_client/components/users/users_component.py
ms_python_client/config.py
ms_python_client/interfaces/__init__.py
ms_python_client/interfaces/ms_client_interface.py
ms_python_client/ms_api_client.py
ms_python_client/services/__init__.py
ms_python_client/services/oauth2_flow.py
ms_python_client/utils/__init__.py
ms_python_client/utils/error.py
ms_python_client/utils/event_generator.py
ms_python_client/utils/file_system.py
ms_python_client/utils/init_from_env.py
ms_python_client/utils/logger.py
ms_python_client-2.0.4.dist-info/LICENSE
ms_python_client-2.0.4.dist-info/METADATA
ms_python_client-2.0.4.dist-info/WHEEL
ms_python_client-2.0.4.dist-info/RECORD
