Metadata-Version: 2.1
Name: ms-python-client
Version: 2.0.4
Summary: This package is used to interact with the microsoft graph API
License: MIT
Author: Samuel Guillemet
Author-email: samuel.guillemet@telecom-sudparis.eu
Requires-Python: >=3.9,<4.0
Classifier: License :: OSI Approved :: MIT License
Classifier: Programming Language :: Python :: 3
Classifier: Programming Language :: Python :: 3.9
Classifier: Programming Language :: Python :: 3.10
Classifier: Programming Language :: Python :: 3.11
Requires-Dist: msal (>=1.22.0,<2.0.0)
Requires-Dist: python-dotenv (>=1.0.0,<2.0.0)
Requires-Dist: requests (>=2.23.0,<3.0.0)
Project-URL: Bug Tracker, https://github.com/cern-vc/ms-python-client/issues
